cabbagok/__init__.py
cabbagok/amqp.py
cabbagok/test_utils.py
cabbagok/utils.py
cabbagok-1.1.0.dist-info/AUTHORS.md
cabbagok-1.1.0.dist-info/METADATA
cabbagok-1.1.0.dist-info/WHEEL
cabbagok-1.1.0.dist-info/top_level.txt
cabbagok-1.1.0.dist-info/zip-safe
cabbagok-1.1.0.dist-info/RECORD
