Metadata-Version: 2.1
Name: cabbagok
Version: 1.1.0
Summary: asyncio-based AMQP client and server for RPC.
Home-page: https://github.com/whiteapfel/cabbagok/
Download-URL: https://pypi.org/project/cabbagok/
Maintainer: WhiteApfel
Maintainer-email: white@pfel.ru
License: Mozilla Public License 2.0
Classifier: Development Status :: 5 - Production/Stable
Classifier: Intended Audience :: Developers
Classifier: License :: OSI Approved :: Mozilla Public License 2.0 (MPL 2.0)
Classifier: Operating System :: OS Independent
Classifier: Programming Language :: Python :: 3.11
Classifier: Programming Language :: Python :: 3.12
Classifier: Topic :: Software Development :: Libraries :: Python Modules
Classifier: Topic :: Utilities
Requires-Python: >=3.11
License-File: AUTHORS.md
Requires-Dist: aioamqp ~=0.15.0
